{
  "content": [
    {
      "content": null,
      "created": "2024-10-22T08:41:23.922187Z",
      "format": null,
      "last_modified": "2024-10-22T08:40:30.634257Z",
      "mimetype": "text/x-python",
      "name": "utils.py",
      "path": "content/data-analysis/lab5-live-camera/utils.py",
      "size": 582,
      "type": "file",
      "writable": true
    },
    {
      "content": null,
      "created": "2024-10-22T08:41:23.918187Z",
      "format": null,
      "last_modified": "2024-10-22T08:40:30.634257Z",
      "mimetype": null,
      "name": "lab5-live-camera.ipynb",
      "path": "content/data-analysis/lab5-live-camera/lab5-live-camera.ipynb",
      "size": 322045,
      "type": "notebook",
      "writable": true
    },
    {
      "content": null,
      "created": "2024-10-22T08:41:23.918187Z",
      "format": null,
      "last_modified": "2024-10-22T08:40:30.630257Z",
      "mimetype": "text/x-python",
      "name": "capture.py",
      "path": "content/data-analysis/lab5-live-camera/capture.py",
      "size": 8595,
      "type": "file",
      "writable": true
    }
  ],
  "created": "2024-10-22T08:41:23.922187Z",
  "format": "json",
  "last_modified": "2024-10-22T08:41:23.922187Z",
  "mimetype": null,
  "name": "lab5-live-camera",
  "path": "content/data-analysis/lab5-live-camera",
  "size": null,
  "type": "directory",
  "writable": true
}